{
    "comp": "h2o",
    "basic": {
        "R": 0.46151805,
        "MW": 18.015268,
        "T_star": 647.096,
        "rho_star": 322.0,
        "Tc": 647.096,
        "rhoc": 322.0,
        "Pc": 22064.0,
        "Tt": 273.16,
        "Pt": 0.611655,
        "rhot_l": 999.793,
        "rhot_v": 0.00485458,
        "P_min": 1e-9,
        "P_max": 1.1e6,
        "rho_max": 1250.0,
        "T_min": 235,
        "T_max": 1300
    },
    "eos": {
        "reference": [
            "International Association for the Properties of Water and Steam (2016).",
            "    IAPWS R6-95 (2016), Revised Release on the IAPWS Formulation 1995 for",
            "    the Properties of Ordinary Water Substance for General Scientific Use.",
            "    URL: http://iapws.org/relguide/IAPWS95-2016.pdf",
            "Wagner, W.,  A. Pruss (2002). The IAPWS Formulation 1995 for the",
            "    Thermodynamic Properties of Ordinary Water Substance for General and",
            "    Scientific Use. J. Phys. Chem. Ref. Data, 31, 387-535."
        ],
        "ideal_terms":[
          {
            "ideal_type": 1,
            "a":[
                -8.3204464837497,
                6.6832105275932
            ]
            },
          {
            "ideal_type": 2,
            "a": 3.00632            
          },
          
          {
            "ideal_type": 3,
            "n": [
                0.012436,
                0.97315,
                1.2795,
                0.96956,
                0.24873
              ],
              "t": [
                1.28728967,
                3.53734222,
                7.74073708,
                9.24437796,
                27.5075105
              ]
          }
        ],
        "residual_terms":[
            {
              "residual_type": 1,
              "d": [
                  1,
                  1,
                  1,
                  2,
                  2,
                  3,
                  4
              ],
              "n":[
                  0.012533547935523,
                  7.8957634722828,
                  -8.7803203303561,
                  0.31802509345418,
                  -0.26145533859358,
                  -0.0078199751687981,
                  0.0088089493102134
              ],
              "t":[
                  -0.5,
                  0.875,
                  1,
                  0.5,
                  0.75,
                  0.375,
                  1
              ]
            },
            {
              "residual_type": 7,
              "d": [
                1,
                1,
                1,
                2,
                2,
                3,
                4,
                4,
                5,
                7,
                9,
                10,
                11,
                13,
                15,
                1,
                2,
                2,
                2,
                3,
                4,
                4,
                4,
                5,
                6,
                6,
                7,
                9,
                9,
                9,
                9,
                9,
                10,
                10,
                12,
                3,
                4,
                4,
                5,
                14,
                3,
                6,
                6,
                6
              ],
              "l": [
                1,
                1,
                1,
                1,
                1,
                1,
                1,
                1,
                1,
                1,
                1,
                1,
                1,
                1,
                1,
                2,
                2,
                2,
                2,
                2,
                2,
                2,
                2,
                2,
                2,
                2,
                2,
                2,
                2,
                2,
                2,
                2,
                2,
                2,
                2,
                3,
                3,
                3,
                3,
                4,
                6,
                6,
                6,
                6
              ],
              "g": [
                1,
                1,
                1,
                1,
                1,
                1,
                1,
                1,
                1,
                1,
                1,
                1,
                1,
                1,
                1,
                1,
                1,
                1,
                1,
                1,
                1,
                1,
                1,
                1,
                1,
                1,
                1,
                1,
                1,
                1,
                1,
                1,
                1,
                1,
                1,
                1,
                1,
                1,
                1,
                1,
                1,
                1,
                1,
                1
              ],
              "n": [
                -0.66856572307965,
                0.20433810950965,
                -6.6212605039687e-05,
                -0.19232721156002,
                -0.25709043003438,
                0.16074868486251,
                -0.040092828925807,
                3.9343422603254e-07,
                -7.5941377088144e-06,
                0.00056250979351888,
                -1.5608652257135e-05,
                1.1537996422951e-09,
                3.6582165144204e-07,
                -1.3251180074668e-12,
                -6.2639586912454e-10,
                -0.10793600908932,
                0.017611491008752,
                0.22132295167546,
                -0.40247669763528,
                0.58083399985759,
                0.0049969146990806,
                -0.031358700712549,
                -0.74315929710341,
                0.4780732991548,
                0.020527940895948,
                -0.13636435110343,
                0.014180634400617,
                0.0083326504880713,
                -0.029052336009585,
                0.038615085574206,
                -0.020393486513704,
                -0.0016554050063734,
                0.0019955571979541,
                0.00015870308324157,
                -1.638856834253e-05,
                0.043613615723811,
                0.034994005463765,
                -0.076788197844621,
                0.022446277332006,
                -6.2689710414685e-05,
                -5.5711118565645e-10,
                -0.19905718354408,
                0.31777497330738,
                -0.11841182425981
              ],
              "t": [
              4,
              6,
              12,
              1,
              5,
              4,
              2,
              13,
              9,
              3,
              4,
              11,
              4,
              13,
              1,
              7,
              1,
              9,
              10,
              10,
              3,
              7,
              10,
              10,
              6,
              10,
              10,
              1,
              2,
              3,
              4,
              8,
              6,
              9,
              8,
              16,
              22,
              23,
              23,
              10,
              50,
              44,
              46,
              50
            ]},
            {"residual_type": 2,
            "b": [
            150,
            150,
            250
          ],
          "d": [
            3,
            3,
            3
          ],
          "e": [
            1,
            1,
            1
          ],
          "a": [
            20,
            20,
            20
          ],
          "g": [
            1.21,
            1.21,
            1.25
          ],
          "n": [
            -31.306260323435,
            31.546140237781,
            -2521.3154341695
          ],
          "t": [
            0,
            1,
            4
          ]
        },
            {"residual_type": 8,
            "A": [
            0.32,
            0.32
          ],
          "B": [
            0.2,
            0.2
          ],
          "C": [
            28,
            32
          ],
          "D": [
            700,
            800
          ],
          "a": [
            3.5,
            3.5
          ],
          "b": [
            0.85,
            0.95
          ],
          "beta": [
            0.3,
            0.3
          ],
          "n": [
            -0.14874640856724,
            0.31806110878444
          ]
        }
        ]
    },
    "aux": {
        "reference": [
            "Wagner, W.,  A. Pruss (2002). The IAPWS Formulation 1995 for the",
            "    Thermodynamic Properties of Ordinary Water Substance for General and",
            "    Scientific Use. J. Phys. Chem. Ref. Data, 31, 387-535."
        ],
        "delta_l_sat_approx": {
            "c": 1.001,
            "n": {
                "1": 1.99274064,
                "2": 1.09965342,
                "3": -0.510839303,
                "4": -1.75493479,
                "5": -45.5170352,
                "6": -6.74694450e5
            },
            "t": {
                "1": 0.3333333333333333,
                "2": 0.6666666666666666,
                "3": 1.6666666666666667,
                "4": 5.333333333333333,
                "5": 14.333333333333333,
                "6": 36.666666666666666
            },
            "type": 1
        },
        "delta_v_sat_approx": {
            "c": 1,
            "n": {
                "1": -2.03150240,
                "2": -2.68302940,
                "3": -5.38626492,
                "4": -17.2991605,
                "5": -44.7586581,
                "6": -63.9201063
            },
            "t": {
                "1": 0.3333333333333333,
                "2": 0.6666666666666666,
                "3": 1.3333333333333333,
                "4": 3.0,
                "5": 6.166666666666667,
                "6": 11.833333333333333
            },
            "type": 2
        }
    },
    "transport": {
        "thermal_conductivity": {
            "reference": [
                "International Association for the Properties of Water and Steam (2011). IAPWS",
                "    R15-11, Release on the IAPWS Formulation 2011 for the Thermal Conductivity",
                "    of Ordinary Water Substance. URL: http://iapws.org/relguide/ThCond.pdf"
            ]
        },
        "viscosity": {
            "reference": [
                "International Association for the Properties of Water and Steam (2008).",
                "    IAPWS R12-08, Release on the IAPWS Formulation 2008 for the Viscosity",
                "    of Ordinary Water Substance. URL: http://iapws.org/relguide/visc.pdf"
            ]
        },
        "surface_tension": {
            "reference": [
                "Mulero, A., I. Cachadina, Parra, M., Recommended Correlations for the Surface ",
                "    Tension of Common Fluids, J. Phys. Chem. Ref. Data 41, 043105, (2012)."
            ],
            "Tc": 647.096,
            "s": {
                "0": -130.6, 
                "1": 215.1
            },
            "n": {
                "0": 2.471,
                "1": 1.233
            },
            "type": 1
        }
    }
}